<?xml version="1.0" encoding="utf-8"?><ArrayOfOrder xmlns:xsi="http://www.w3.org/2001/XMLSchema-instance" xmlns:xsd="http://www.w3.org/2001/XMLSchema"><Order><idOfOrder>100000</idOfOrder><CustomerName>Yossi</CustomerName><CustomerMail>Yossi@gmail.com</CustomerMail><CustamerAddress>Eilat</CustamerAddress><DateOfOrder>2023-01-01T04:00:00</DateOfOrder><DateOfShipping>2023-01-01T18:09:28</DateOfShipping><DateOfDelivery>2023-01-07T09:07:33</DateOfDelivery></Order><Order><idOfOrder>100001</idOfOrder><CustomerName>Hadar</CustomerName><CustomerMail>Hadar@gmail.com</CustomerMail><CustamerAddress>Tiberias</CustamerAddress><DateOfOrder>2023-01-01T04:00:00</DateOfOrder><DateOfShipping xsi:nil="true" /><DateOfDelivery xsi:nil="true" /></Order><Order><idOfOrder>100002</idOfOrder><CustomerName>Hadar</CustomerName><CustomerMail>Hadar@gmail.com</CustomerMail><CustamerAddress>Jerusalem</CustamerAddress><DateOfOrder>2023-01-01T04:00:00</DateOfOrder><DateOfShipping xsi:nil="true" /><DateOfDelivery xsi:nil="true" /></Order><Order><idOfOrder>100003</idOfOrder><CustomerName>Moshe</CustomerName><CustomerMail>Moshe@gmail.com</CustomerMail><CustamerAddress>Eilat</CustamerAddress><DateOfOrder>2023-01-01T04:00:00</DateOfOrder><DateOfShipping>2023-01-01T16:02:35</DateOfShipping><DateOfDelivery>2023-01-08T12:26:45</DateOfDelivery></Order><Order><idOfOrder>100004</idOfOrder><CustomerName>Yossi</CustomerName><CustomerMail>Yossi@gmail.com</CustomerMail><CustamerAddress>Eilat</CustamerAddress><DateOfOrder>2023-01-01T04:00:00</DateOfOrder><DateOfShipping>2023-01-03T10:31:09</DateOfShipping><DateOfDelivery>2023-01-05T06:48:51</DateOfDelivery></Order><Order><idOfOrder>100005</idOfOrder><CustomerName>Hadar</CustomerName><CustomerMail>Hadar@gmail.com</CustomerMail><CustamerAddress>Tel aviv</CustamerAddress><DateOfOrder>2023-01-01T04:00:00</DateOfOrder><DateOfShipping xsi:nil="true" /><DateOfDelivery xsi:nil="true" /></Order><Order><idOfOrder>100006</idOfOrder><CustomerName>Moshe</CustomerName><CustomerMail>Moshe@gmail.com</CustomerMail><CustamerAddress>Jerusalem</CustamerAddress><DateOfOrder>2023-01-01T04:00:00</DateOfOrder><DateOfShipping xsi:nil="true" /><DateOfDelivery xsi:nil="true" /></Order><Order><idOfOrder>100007</idOfOrder><CustomerName>Moshe</CustomerName><CustomerMail>Moshe@gmail.com</CustomerMail><CustamerAddress>Tiberias</CustamerAddress><DateOfOrder>2023-01-01T04:00:00</DateOfOrder><DateOfShipping xsi:nil="true" /><DateOfDelivery xsi:nil="true" /></Order><Order><idOfOrder>100008</idOfOrder><CustomerName>Hadar</CustomerName><CustomerMail>Hadar@gmail.com</CustomerMail><CustamerAddress>Tiberias</CustamerAddress><DateOfOrder>2023-01-01T04:00:00</DateOfOrder><DateOfShipping>2023-01-03T22:33:01</DateOfShipping><DateOfDelivery>2023-01-10T21:28:26</DateOfDelivery></Order><Order><idOfOrder>100009</idOfOrder><CustomerName>Moshe</CustomerName><CustomerMail>Moshe@gmail.com</CustomerMail><CustamerAddress>Jerusalem</CustamerAddress><DateOfOrder>2023-01-01T04:00:00</DateOfOrder><DateOfShipping>2023-01-03T14:52:19</DateOfShipping><DateOfDelivery>2023-01-09T04:41:34</DateOfDelivery></Order><Order><idOfOrder>100010</idOfOrder><CustomerName>Sapir</CustomerName><CustomerMail>Sapir@gmail.com</CustomerMail><CustamerAddress>Jerusalem</CustamerAddress><DateOfOrder>2023-01-01T04:00:00</DateOfOrder><DateOfShipping>2023-01-02T05:39:53</DateOfShipping><DateOfDelivery>2023-01-07T10:09:32</DateOfDelivery></Order><Order><idOfOrder>100011</idOfOrder><CustomerName>Dani</CustomerName><CustomerMail>Dani@gmail.com</CustomerMail><CustamerAddress>Jerusalem</CustamerAddress><DateOfOrder>2023-01-01T04:00:00</DateOfOrder><DateOfShipping>2023-01-01T08:28:34</DateOfShipping><DateOfDelivery>2023-01-02T03:05:01</DateOfDelivery></Order><Order><idOfOrder>100012</idOfOrder><CustomerName>Avi</CustomerName><CustomerMail>Avi@gmail.com</CustomerMail><CustamerAddress>Tel aviv</CustamerAddress><DateOfOrder>2023-01-01T04:00:00</DateOfOrder><DateOfShipping>2023-01-03T20:55:14</DateOfShipping><DateOfDelivery>2023-01-09T07:26:53</DateOfDelivery></Order><Order><idOfOrder>100013</idOfOrder><CustomerName>Yossi</CustomerName><CustomerMail>Yossi@gmail.com</CustomerMail><CustamerAddress>Erzeliya</CustamerAddress><DateOfOrder>2023-01-01T04:00:00</DateOfOrder><DateOfShipping>2023-01-08T00:23:34</DateOfShipping><DateOfDelivery xsi:nil="true" /></Order><Order><idOfOrder>100014</idOfOrder><CustomerName>Moshe</CustomerName><CustomerMail>Moshe@gmail.com</CustomerMail><CustamerAddress>Tel aviv</CustamerAddress><DateOfOrder>2023-01-01T04:00:00</DateOfOrder><DateOfShipping>2023-01-03T10:33:25</DateOfShipping><DateOfDelivery>2023-01-04T09:55:21</DateOfDelivery></Order><Order><idOfOrder>100015</idOfOrder><CustomerName>Hadar</CustomerName><CustomerMail>Hadar@gmail.com</CustomerMail><CustamerAddress>Erzeliya</CustamerAddress><DateOfOrder>2023-01-01T04:00:00</DateOfOrder><DateOfShipping>2023-01-07T12:26:07</DateOfShipping><DateOfDelivery>2023-01-08T17:41:05</DateOfDelivery></Order><Order><idOfOrder>100016</idOfOrder><CustomerName>Avi</CustomerName><CustomerMail>Avi@gmail.com</CustomerMail><CustamerAddress>Erzeliya</CustamerAddress><DateOfOrder>2023-01-01T04:00:00</DateOfOrder><DateOfShipping xsi:nil="true" /><DateOfDelivery xsi:nil="true" /></Order><Order><idOfOrder>100017</idOfOrder><CustomerName>Hadar</CustomerName><CustomerMail>Hadar@gmail.com</CustomerMail><CustamerAddress>Jerusalem</CustamerAddress><DateOfOrder>2023-01-01T04:00:00</DateOfOrder><DateOfShipping>2023-01-06T06:31:47</DateOfShipping><DateOfDelivery xsi:nil="true" /></Order><Order><idOfOrder>100018</idOfOrder><CustomerName>Yossi</CustomerName><CustomerMail>Yossi@gmail.com</CustomerMail><CustamerAddress>Jerusalem</CustamerAddress><DateOfOrder>2023-01-01T04:00:00</DateOfOrder><DateOfShipping>2023-01-03T21:01:10</DateOfShipping><DateOfDelivery>2023-01-07T14:14:40</DateOfDelivery></Order><Order><idOfOrder>100019</idOfOrder><CustomerName>Yossi</CustomerName><CustomerMail>Yossi@gmail.com</CustomerMail><CustamerAddress>Eilat</CustamerAddress><DateOfOrder>2023-01-01T04:00:00</DateOfOrder><DateOfShipping>2023-01-01T08:58:17</DateOfShipping><DateOfDelivery>2023-01-06T14:40:33</DateOfDelivery></Order></ArrayOfOrder>