<?xml version="1.0" encoding="utf-8"?><ArrayOfProduct xmlns:xsi="http://www.w3.org/2001/XMLSchema-instance" xmlns:xsd="http://www.w3.org/2001/XMLSchema"><Product><idOfProduct>296632</idOfProduct><Name>BMW</Name><ProductCategory>Jeep</ProductCategory><Price>650000</Price><InStock>1</InStock></Product><Product><idOfProduct>961380</idOfProduct><Name>Tesla</Name><ProductCategory>Collectors</ProductCategory><Price>500000</Price><InStock>4</InStock></Product><Product><idOfProduct>702103</idOfProduct><Name>BMW</Name><ProductCategory>Gears</ProductCategory><Price>200000</Price><InStock>2</InStock></Product><Product><idOfProduct>719610</idOfProduct><Name>Lamborgini</Name><ProductCategory>Collectors</ProductCategory><Price>200000</Price><InStock>1</InStock></Product><Product><idOfProduct>686579</idOfProduct><Name>Lamborgini</Name><ProductCategory>Familly</ProductCategory><Price>100000</Price><InStock>0</InStock></Product><Product><idOfProduct>414240</idOfProduct><Name>Ferrari</Name><ProductCategory>Sport</ProductCategory><Price>100000</Price><InStock>4</InStock></Product><Product><idOfProduct>931852</idOfProduct><Name>Tesla</Name><ProductCategory>Collectors</ProductCategory><Price>100000</Price><InStock>3</InStock></Product><Product><idOfProduct>809129</idOfProduct><Name>Corvette</Name><ProductCategory>Race</ProductCategory><Price>250000</Price><InStock>2</InStock></Product><Product><idOfProduct>231294</idOfProduct><Name>Jeep</Name><ProductCategory>Familly</ProductCategory><Price>100000</Price><InStock>2</InStock></Product><Product><idOfProduct>319978</idOfProduct><Name>Porche</Name><ProductCategory>Familly</ProductCategory><Price>500000</Price><InStock>2</InStock></Product></ArrayOfProduct>